pybel/__init__.py
pybel/__main__.py
pybel/canonicalize.py
pybel/cli.py
pybel/config.py
pybel/constants.py
pybel/exceptions.py
pybel/grounding.py
pybel/language.py
pybel/repository.py
pybel/tokens.py
pybel/typing.py
pybel/utils.py
pybel/version.py
pybel/apps/parser.py
pybel/dsl/__init__.py
pybel/dsl/constants.py
pybel/dsl/edges.py
pybel/dsl/exc.py
pybel/dsl/namespaces.py
pybel/dsl/node_classes.py
pybel/examples/__init__.py
pybel/examples/ampk_example.py
pybel/examples/braf_example.py
pybel/examples/egf_example.py
pybel/examples/homology_example.py
pybel/examples/sialic_acid_example.py
pybel/examples/statin_example.py
pybel/examples/tloc_example.py
pybel/examples/various_example.py
pybel/examples/vegf_example.py
pybel/io/__init__.py
pybel/io/api.py
pybel/io/aws.py
pybel/io/bel_commons_client.py
pybel/io/biodati_client.py
pybel/io/cx.py
pybel/io/emmaa.py
pybel/io/exc.py
pybel/io/extras.py
pybel/io/fraunhofer_orientdb.py
pybel/io/gpickle.py
pybel/io/graphdati.py
pybel/io/graphml.py
pybel/io/hipathia.py
pybel/io/indra.py
pybel/io/jgif.py
pybel/io/jinja_utils.py
pybel/io/line_utils.py
pybel/io/lines.py
pybel/io/neo4j.py
pybel/io/nodelink.py
pybel/io/pykeen.py
pybel/io/pynpa.py
pybel/io/sbel.py
pybel/io/spia.py
pybel/io/umbrella_nodelink.py
pybel/io/utils.py
pybel/io/web.py
pybel/io/hetionet/__init__.py
pybel/io/hetionet/__main__.py
pybel/io/hetionet/cli.py
pybel/io/hetionet/constants.py
pybel/io/hetionet/hetionet.py
pybel/io/jupyter/__init__.py
pybel/io/jupyter/constants.py
pybel/io/jupyter/inline.py
pybel/io/jupyter/visualization.py
pybel/io/jupyter/templates/graph_template.html
pybel/io/jupyter/templates/pybel_jupyter.js
pybel/io/jupyter/templates/pybel_vis.js
pybel/io/triples/__init__.py
pybel/io/triples/api.py
pybel/io/triples/converters.py
pybel/io/tsv/__init__.py
pybel/io/tsv/api.py
pybel/io/tsv/converters.py
pybel/manager/__init__.py
pybel/manager/base_manager.py
pybel/manager/cache_manager.py
pybel/manager/citation_utils.py
pybel/manager/database_io.py
pybel-0.15.5.dist-info/LICENSE
pybel-0.15.5.dist-info/METADATA
pybel-0.15.5.dist-info/WHEEL
pybel-0.15.5.dist-info/entry_points.txt
pybel-0.15.5.dist-info/top_level.txt
pybel-0.15.5.dist-info/RECORD
