Metadata-Version: 2.1
Name: pybel
Version: 0.15.5
Summary: Parsing, validation, compilation, and data exchange of Biological Expression Language (BEL)
Home-page: https://github.com/pybel/pybel
Author: Charles Tapley Hoyt
Author-email: cthoyt@gmail.com
Maintainer: Charles Tapley Hoyt
Maintainer-email: cthoyt@gmail.com
License: MIT
Download-URL: https://github.com/pybel/pybel/releases
Project-URL: Bug Tracker, https://github.com/pybel/pybel/issues
Project-URL: Source Code, https://github.com/pybel/pybel
Project-URL: Documentation, https://pybel.readthedocs.io
Keywords: Biological Expression Language,BEL,Domain Specific Language,DSL,Systems Biology,Networks Biology
Platform: UNKNOWN
Classifier: Development Status :: 5 - Production/Stable
Classifier: Environment :: Console
Classifier: Intended Audience :: Developers
Classifier: Intended Audience :: Science/Research
Classifier: License :: OSI Approved :: MIT License
Classifier: Operating System :: OS Independent
Classifier: Programming Language :: Python
Classifier: Programming Language :: Python :: 3.10
Classifier: Programming Language :: Python :: 3.9
Classifier: Programming Language :: Python :: 3.8
Classifier: Programming Language :: Python :: 3.7
Classifier: Programming Language :: Python :: 3.6
Classifier: Programming Language :: Python :: 3 :: Only
Classifier: Topic :: Scientific/Engineering :: Bio-Informatics
Classifier: Topic :: Scientific/Engineering :: Chemistry
Requires-Python: >=3.6
License-File: LICENSE
Requires-Dist: networkx (>=2.4)
Requires-Dist: sqlalchemy
Requires-Dist: click
Requires-Dist: click-plugins
Requires-Dist: bel-resources (>=0.0.3)
Requires-Dist: more-itertools
Requires-Dist: requests
Requires-Dist: requests-file
Requires-Dist: pyparsing
Requires-Dist: tqdm
Requires-Dist: humanize
Requires-Dist: tabulate
Requires-Dist: pandas
Requires-Dist: jsonschema
Requires-Dist: bioregistry
Requires-Dist: ratelimit
Requires-Dist: pystow (>=0.1.2)
Requires-Dist: psycopg2-binary
Requires-Dist: dataclasses ; python_version < "3.7"
Requires-Dist: pickle5 ; python_version < "3.8"
Provides-Extra: docs
Requires-Dist: sphinx ; extra == 'docs'
Requires-Dist: sphinx-rtd-theme ; extra == 'docs'
Requires-Dist: sphinx-click ; extra == 'docs'
Requires-Dist: sphinx-autodoc-typehints ; extra == 'docs'
Provides-Extra: grounding
Requires-Dist: pyobo ; extra == 'grounding'
Requires-Dist: protmapper ; extra == 'grounding'
Provides-Extra: indra
Requires-Dist: indra ; extra == 'indra'
Provides-Extra: jupyter
Requires-Dist: jinja2 ; extra == 'jupyter'
Requires-Dist: ipython ; extra == 'jupyter'
Provides-Extra: neo4j
Requires-Dist: py2neo ; extra == 'neo4j'
